{
  "nodes": [
    {
      "id": "0ef9b348-b509-4ccd-abf5-d3eb5f97b0d6",
      "name": "Calculating Maximum Support Request",
      "type": "inputNode",
      "position": {
        "x": -100,
        "y": 295
      }
    },
    {
      "id": "95a8fd76-0915-48d9-b716-11577923dd7b",
      "name": "Single or Couple",
      "type": "switchNode",
      "content": {
        "statements": [
          {
            "id": "371816d5-dfad-494e-af27-f68367b8a574",
            "condition": "person2age != null"
          },
          {
            "id": "71d825d5-b9e2-45a6-b106-4cbe576f379a",
            "condition": ""
          }
        ]
      },
      "position": {
        "x": 330,
        "y": 260
      }
    },
    {
      "id": "42de2c3f-f9c0-4acf-93bd-f06a3adf5ef2",
      "name": "Single Calculation",
      "type": "decisionTableNode",
      "content": {
        "hitPolicy": "first",
        "inputs": [
          {
            "id": "eae2f93a-2685-4bfa-b8c0-9efbf0e254ca",
            "name": "Age",
            "type": "expression",
            "field": "person1age"
          },
          {
            "id": "564db848-f951-461f-b572-0b14f4499e05",
            "name": "PPMB Status",
            "type": "expression",
            "field": "person1hasPPMBStatus",
            "defaultValue": "false"
          },
          {
            "id": "d2d8ee7f-7eb0-4576-9737-5376bdb9e48c",
            "name": "Family Unit Size",
            "type": "expression",
            "field": "familyUnitSize"
          }
        ],
        "outputs": [
          {
            "id": "aed03151-e8ba-4284-b360-29b70f07a573",
            "name": "Maximum Support Amount",
            "type": "expression",
            "field": "maximumSupportAmount"
          }
        ],
        "rules": [
          {
            "_id": "1e20c7a4-e759-4f2e-ae7b-03b409963a6e",
            "_description": "",
            "564db848-f951-461f-b572-0b14f4499e05": "",
            "aed03151-e8ba-4284-b360-29b70f07a573": "0",
            "d2d8ee7f-7eb0-4576-9737-5376bdb9e48c": "== 1",
            "eae2f93a-2685-4bfa-b8c0-9efbf0e254ca": ""
          },
          {
            "_id": "553c0645-0282-429a-b473-9d09a1886798",
            "_description": "",
            "564db848-f951-461f-b572-0b14f4499e05": "false",
            "aed03151-e8ba-4284-b360-29b70f07a573": "610",
            "d2d8ee7f-7eb0-4576-9737-5376bdb9e48c": "> 1",
            "eae2f93a-2685-4bfa-b8c0-9efbf0e254ca": "< 65"
          },
          {
            "_id": "45c88acb-3683-43fe-ac20-c06e07cd6882",
            "_description": "",
            "564db848-f951-461f-b572-0b14f4499e05": "true",
            "aed03151-e8ba-4284-b360-29b70f07a573": "660",
            "d2d8ee7f-7eb0-4576-9737-5376bdb9e48c": "> 1",
            "eae2f93a-2685-4bfa-b8c0-9efbf0e254ca": "< 65"
          },
          {
            "_id": "9132f40b-c333-4211-914a-3c61ed60724a",
            "_description": "",
            "564db848-f951-461f-b572-0b14f4499e05": "",
            "aed03151-e8ba-4284-b360-29b70f07a573": "910",
            "d2d8ee7f-7eb0-4576-9737-5376bdb9e48c": "> 1",
            "eae2f93a-2685-4bfa-b8c0-9efbf0e254ca": ">= 65"
          }
        ]
      },
      "position": {
        "x": 660,
        "y": 475
      }
    },
    {
      "id": "87a78f50-78f3-4ed8-9368-bcbeb110516d",
      "name": "Support Amount Response",
      "type": "outputNode",
      "position": {
        "x": 1255,
        "y": 385
      }
    },
    {
      "id": "b96f4ee8-7085-484c-b4cd-16990d429dbf",
      "type": "switchNode",
      "position": {
        "x": 665,
        "y": 115
      },
      "name": "Dependents?",
      "content": {
        "statements": [
          {
            "id": "192d22af-87a0-4e28-afa1-7b24a473d106",
            "condition": "familyUnitSize > 2"
          },
          {
            "id": "04132164-4a91-4fc3-bb56-e8e8e5d6efcd",
            "condition": ""
          }
        ]
      }
    },
    {
      "id": "04bd3143-711e-4896-9598-8783989c1be2",
      "name": "Couple",
      "type": "decisionTableNode",
      "content": {
        "hitPolicy": "first",
        "inputs": [
          {
            "id": "f60aecf1-41b4-46cb-be41-da2a321eace7",
            "name": "Person 1 Age",
            "type": "expression",
            "field": "person1age"
          },
          {
            "id": "2228d8e9-e32a-47f2-8905-dcd24315fb44",
            "name": "Person 1 PPMB Status",
            "type": "expression",
            "field": "person1hasPPMBStatus"
          },
          {
            "id": "4487d5a3-b08e-4925-9278-cc8fa223f4c3",
            "type": "expression",
            "field": "person1Warrant",
            "name": "Person 1 Warrant Issued"
          },
          {
            "id": "8abc2014-5c23-42a9-9ba7-0b106e9158d2",
            "name": "Person 2 Age",
            "type": "expression",
            "field": "person2age"
          },
          {
            "id": "b816ade1-bef2-42de-9d6f-4c389b8c16a5",
            "name": "Person 2 PPMB Status",
            "type": "expression",
            "field": "person2hasPPMBStatus"
          },
          {
            "id": "bc180d95-6234-45ef-a7eb-b3344c25013b",
            "type": "expression",
            "field": "person2Warrant",
            "name": "Person 2 Warrant Issued"
          }
        ],
        "outputs": [
          {
            "id": "20f8d6b0-0f96-4f1a-9547-24c947b7b5c6",
            "name": "Maximum Support Amount",
            "type": "expression",
            "field": "maximumSupportAmount"
          }
        ],
        "rules": [
          {
            "_id": "1f0000ea-9710-4dd9-a8aa-129bd8091ebb",
            "_description": "Both applicants/recipients are under 65 years of age and a warrant has been issued for one",
            "f60aecf1-41b4-46cb-be41-da2a321eace7": "< 65",
            "2228d8e9-e32a-47f2-8905-dcd24315fb44": "false",
            "4487d5a3-b08e-4925-9278-cc8fa223f4c3": "true",
            "8abc2014-5c23-42a9-9ba7-0b106e9158d2": "< 65",
            "b816ade1-bef2-42de-9d6f-4c389b8c16a5": "false",
            "bc180d95-6234-45ef-a7eb-b3344c25013b": "== null or == false",
            "20f8d6b0-0f96-4f1a-9547-24c947b7b5c6": "610"
          },
          {
            "_id": "e592c9e8-8f70-4b62-b987-5dc6dcb952da",
            "_description": "Both applicants/recipients are under 65 years of age and a warrant has been issued for one",
            "f60aecf1-41b4-46cb-be41-da2a321eace7": "< 65",
            "2228d8e9-e32a-47f2-8905-dcd24315fb44": "false",
            "4487d5a3-b08e-4925-9278-cc8fa223f4c3": "== null or == false",
            "8abc2014-5c23-42a9-9ba7-0b106e9158d2": "< 65",
            "b816ade1-bef2-42de-9d6f-4c389b8c16a5": "false",
            "bc180d95-6234-45ef-a7eb-b3344c25013b": "true",
            "20f8d6b0-0f96-4f1a-9547-24c947b7b5c6": "610"
          },
          {
            "_id": "095a879b-4eee-4957-bd00-bf4edea34c4a",
            "_description": "One applicant/recipient is under 65 years of age and is a person who has persistent multiple barriers to employment, and a warrant has been issued for that applicant/recipient, and the other is under 65 years of age",
            "f60aecf1-41b4-46cb-be41-da2a321eace7": "< 65",
            "2228d8e9-e32a-47f2-8905-dcd24315fb44": "true",
            "4487d5a3-b08e-4925-9278-cc8fa223f4c3": "true",
            "8abc2014-5c23-42a9-9ba7-0b106e9158d2": "< 65",
            "b816ade1-bef2-42de-9d6f-4c389b8c16a5": "false",
            "bc180d95-6234-45ef-a7eb-b3344c25013b": "== null or == false",
            "20f8d6b0-0f96-4f1a-9547-24c947b7b5c6": "610"
          },
          {
            "_id": "6f093644-523c-44da-a8d9-86c635d06f8a",
            "_description": "One applicant/recipient is under 65 years of age and is a person who has persistent multiple barriers to employment, and a warrant has been issued for that applicant/recipient, and the other is under 65 years of age",
            "f60aecf1-41b4-46cb-be41-da2a321eace7": "< 65",
            "2228d8e9-e32a-47f2-8905-dcd24315fb44": "false",
            "4487d5a3-b08e-4925-9278-cc8fa223f4c3": "== null or == false",
            "8abc2014-5c23-42a9-9ba7-0b106e9158d2": "< 65",
            "b816ade1-bef2-42de-9d6f-4c389b8c16a5": "true",
            "bc180d95-6234-45ef-a7eb-b3344c25013b": "true",
            "20f8d6b0-0f96-4f1a-9547-24c947b7b5c6": "610"
          },
          {
            "_id": "06a7cc69-3468-49f4-a30c-eba466cfc6db",
            "_description": "One applicant/recipient is under 65 years of age and is a person who has persistent multiple barriers to employment, and the other is under 65 years of age and a warrant has been issued for that applicant/recipient.",
            "f60aecf1-41b4-46cb-be41-da2a321eace7": "< 65",
            "2228d8e9-e32a-47f2-8905-dcd24315fb44": "true",
            "4487d5a3-b08e-4925-9278-cc8fa223f4c3": "== null or == false",
            "8abc2014-5c23-42a9-9ba7-0b106e9158d2": "< 65",
            "b816ade1-bef2-42de-9d6f-4c389b8c16a5": "false",
            "bc180d95-6234-45ef-a7eb-b3344c25013b": "true",
            "20f8d6b0-0f96-4f1a-9547-24c947b7b5c6": "660"
          },
          {
            "_id": "ac31bab6-591f-4639-9643-2ca7ec4f6499",
            "_description": "One applicant/recipient is under 65 years of age and is a person who has persistent multiple barriers to employment, and the other is under 65 years of age and a warrant has been issued for that applicant/recipient.",
            "f60aecf1-41b4-46cb-be41-da2a321eace7": "< 65",
            "2228d8e9-e32a-47f2-8905-dcd24315fb44": "false",
            "4487d5a3-b08e-4925-9278-cc8fa223f4c3": "true",
            "8abc2014-5c23-42a9-9ba7-0b106e9158d2": "< 65",
            "b816ade1-bef2-42de-9d6f-4c389b8c16a5": "true",
            "bc180d95-6234-45ef-a7eb-b3344c25013b": "== null or == false",
            "20f8d6b0-0f96-4f1a-9547-24c947b7b5c6": "660"
          },
          {
            "_id": "9ac364f8-38fe-40f1-a5ae-0abac33d968f",
            "_description": "One applicant/recipient is under 65 years of age and is a person who has persistent multiple barriers to employment and a warrant has been issued for the applicant/recipient, and the other is 65 years of age or older",
            "f60aecf1-41b4-46cb-be41-da2a321eace7": "< 65",
            "2228d8e9-e32a-47f2-8905-dcd24315fb44": "true",
            "4487d5a3-b08e-4925-9278-cc8fa223f4c3": "true",
            "8abc2014-5c23-42a9-9ba7-0b106e9158d2": ">= 65",
            "b816ade1-bef2-42de-9d6f-4c389b8c16a5": "",
            "bc180d95-6234-45ef-a7eb-b3344c25013b": "== null or == false",
            "20f8d6b0-0f96-4f1a-9547-24c947b7b5c6": "910"
          },
          {
            "_id": "ca24b4c8-091c-4499-8e24-ea19f2ac5a0e",
            "_description": "One applicant/recipient is under 65 years of age and is a person who has persistent multiple barriers to employment and a warrant has been issued for the applicant/recipient, and the other is 65 years of age or older",
            "f60aecf1-41b4-46cb-be41-da2a321eace7": ">= 65",
            "2228d8e9-e32a-47f2-8905-dcd24315fb44": "",
            "4487d5a3-b08e-4925-9278-cc8fa223f4c3": "== null or == false",
            "8abc2014-5c23-42a9-9ba7-0b106e9158d2": "< 65",
            "b816ade1-bef2-42de-9d6f-4c389b8c16a5": "true",
            "bc180d95-6234-45ef-a7eb-b3344c25013b": "true",
            "20f8d6b0-0f96-4f1a-9547-24c947b7b5c6": "910"
          },
          {
            "_id": "56f1a164-a279-4590-bc65-4c61686f75ee",
            "_description": "One applicant/recipient is under 65 years of age and is a person who has persistent multiple barriers to employment, and the other is 65 years of age or older and a warrant has been issued for that applicant/recipient",
            "f60aecf1-41b4-46cb-be41-da2a321eace7": "< 65",
            "2228d8e9-e32a-47f2-8905-dcd24315fb44": "true",
            "4487d5a3-b08e-4925-9278-cc8fa223f4c3": "== null or == false",
            "8abc2014-5c23-42a9-9ba7-0b106e9158d2": ">= 65",
            "b816ade1-bef2-42de-9d6f-4c389b8c16a5": "",
            "bc180d95-6234-45ef-a7eb-b3344c25013b": "true",
            "20f8d6b0-0f96-4f1a-9547-24c947b7b5c6": "660"
          },
          {
            "_id": "3a307cb8-6e34-438a-b3b0-3fa998feabff",
            "_description": "One applicant/recipient is under 65 years of age and is a person who has persistent multiple barriers to employment, and the other is 65 years of age or older and a warrant has been issued for that applicant/recipient",
            "f60aecf1-41b4-46cb-be41-da2a321eace7": ">= 65",
            "2228d8e9-e32a-47f2-8905-dcd24315fb44": "",
            "4487d5a3-b08e-4925-9278-cc8fa223f4c3": "true",
            "8abc2014-5c23-42a9-9ba7-0b106e9158d2": "< 65",
            "b816ade1-bef2-42de-9d6f-4c389b8c16a5": "true",
            "bc180d95-6234-45ef-a7eb-b3344c25013b": "== null or == false",
            "20f8d6b0-0f96-4f1a-9547-24c947b7b5c6": "660"
          },
          {
            "_id": "d071365d-11fa-46a1-8cfc-137b1f9b42c5",
            "_description": "One applicant/recipient is under 65 years of age and a warrant has been issued for that applicant/recipient, and the other is 65 years of age or older",
            "f60aecf1-41b4-46cb-be41-da2a321eace7": "< 65",
            "2228d8e9-e32a-47f2-8905-dcd24315fb44": "false",
            "4487d5a3-b08e-4925-9278-cc8fa223f4c3": "true",
            "8abc2014-5c23-42a9-9ba7-0b106e9158d2": ">= 65",
            "b816ade1-bef2-42de-9d6f-4c389b8c16a5": "",
            "bc180d95-6234-45ef-a7eb-b3344c25013b": "== null or == false",
            "20f8d6b0-0f96-4f1a-9547-24c947b7b5c6": "910"
          },
          {
            "_id": "9df7b0de-a1b8-4792-8ab0-6d965de8c202",
            "_description": "One applicant/recipient is under 65 years of age and a warrant has been issued for that applicant/recipient, and the other is 65 years of age or older",
            "f60aecf1-41b4-46cb-be41-da2a321eace7": ">= 65",
            "2228d8e9-e32a-47f2-8905-dcd24315fb44": "",
            "4487d5a3-b08e-4925-9278-cc8fa223f4c3": "== null or == false",
            "8abc2014-5c23-42a9-9ba7-0b106e9158d2": "< 65",
            "b816ade1-bef2-42de-9d6f-4c389b8c16a5": "false",
            "bc180d95-6234-45ef-a7eb-b3344c25013b": "true",
            "20f8d6b0-0f96-4f1a-9547-24c947b7b5c6": "910"
          },
          {
            "_id": "a19e5cfe-b177-4cde-9614-18c30c578b64",
            "_description": "One applicant/recipient is under 65 years of age, and the other is 65 years of age or older and a warrant has been issued for that applicant/recipient",
            "f60aecf1-41b4-46cb-be41-da2a321eace7": "< 65",
            "2228d8e9-e32a-47f2-8905-dcd24315fb44": "",
            "4487d5a3-b08e-4925-9278-cc8fa223f4c3": "== null or == false",
            "8abc2014-5c23-42a9-9ba7-0b106e9158d2": ">= 65",
            "b816ade1-bef2-42de-9d6f-4c389b8c16a5": "",
            "bc180d95-6234-45ef-a7eb-b3344c25013b": "true",
            "20f8d6b0-0f96-4f1a-9547-24c947b7b5c6": "610"
          },
          {
            "_id": "fe921a96-236b-46d2-9b01-56c38328cb7c",
            "_description": "One applicant/recipient is under 65 years of age, and the other is 65 years of age or older and a warrant has been issued for that applicant/recipient",
            "f60aecf1-41b4-46cb-be41-da2a321eace7": ">= 65",
            "2228d8e9-e32a-47f2-8905-dcd24315fb44": "",
            "4487d5a3-b08e-4925-9278-cc8fa223f4c3": "true",
            "8abc2014-5c23-42a9-9ba7-0b106e9158d2": "< 65",
            "b816ade1-bef2-42de-9d6f-4c389b8c16a5": "",
            "bc180d95-6234-45ef-a7eb-b3344c25013b": "== null or == false",
            "20f8d6b0-0f96-4f1a-9547-24c947b7b5c6": "610"
          },
          {
            "_id": "fec76ef4-5704-4a61-bc4a-5992a9c51948",
            "_description": "Both applicants/recipients are 65 years of age or older, and a warrant has been issued for one",
            "f60aecf1-41b4-46cb-be41-da2a321eace7": ">= 65",
            "2228d8e9-e32a-47f2-8905-dcd24315fb44": "",
            "4487d5a3-b08e-4925-9278-cc8fa223f4c3": "true",
            "8abc2014-5c23-42a9-9ba7-0b106e9158d2": ">= 65",
            "b816ade1-bef2-42de-9d6f-4c389b8c16a5": "",
            "bc180d95-6234-45ef-a7eb-b3344c25013b": "== null or == false",
            "20f8d6b0-0f96-4f1a-9547-24c947b7b5c6": "910"
          },
          {
            "_id": "a99eb609-b8d6-4637-8638-70dc62ae94f6",
            "_description": "Both applicants/recipients are 65 years of age or older, and a warrant has been issued for one",
            "f60aecf1-41b4-46cb-be41-da2a321eace7": ">= 65",
            "2228d8e9-e32a-47f2-8905-dcd24315fb44": "",
            "4487d5a3-b08e-4925-9278-cc8fa223f4c3": "== null or == false",
            "8abc2014-5c23-42a9-9ba7-0b106e9158d2": ">= 65",
            "b816ade1-bef2-42de-9d6f-4c389b8c16a5": "",
            "bc180d95-6234-45ef-a7eb-b3344c25013b": "true",
            "20f8d6b0-0f96-4f1a-9547-24c947b7b5c6": "910"
          },
          {
            "_id": "5694c416-8daa-4ff8-83b6-82a748fac66f",
            "_description": "Both applicants/recipients are under 65 years of age and both have persistent multiple barriers to employment, and a warrant has been issued for one",
            "f60aecf1-41b4-46cb-be41-da2a321eace7": "< 65",
            "2228d8e9-e32a-47f2-8905-dcd24315fb44": "true",
            "4487d5a3-b08e-4925-9278-cc8fa223f4c3": "true",
            "8abc2014-5c23-42a9-9ba7-0b106e9158d2": "< 65",
            "b816ade1-bef2-42de-9d6f-4c389b8c16a5": "true",
            "bc180d95-6234-45ef-a7eb-b3344c25013b": "== null or == false",
            "20f8d6b0-0f96-4f1a-9547-24c947b7b5c6": "660"
          },
          {
            "_id": "dbc79ff1-ef25-4a49-a19a-17b2bc1eb797",
            "_description": "Both applicants/recipients are under 65 years of age and both have persistent multiple barriers to employment, and a warrant has been issued for one",
            "f60aecf1-41b4-46cb-be41-da2a321eace7": "< 65",
            "2228d8e9-e32a-47f2-8905-dcd24315fb44": "true",
            "4487d5a3-b08e-4925-9278-cc8fa223f4c3": "== null or == false",
            "8abc2014-5c23-42a9-9ba7-0b106e9158d2": "< 65",
            "b816ade1-bef2-42de-9d6f-4c389b8c16a5": "true",
            "bc180d95-6234-45ef-a7eb-b3344c25013b": "true",
            "20f8d6b0-0f96-4f1a-9547-24c947b7b5c6": "660"
          },
          {
            "_id": "6c50f0cb-a02f-44b3-941f-a0980827dd2c",
            "f60aecf1-41b4-46cb-be41-da2a321eace7": "",
            "2228d8e9-e32a-47f2-8905-dcd24315fb44": "",
            "4487d5a3-b08e-4925-9278-cc8fa223f4c3": "",
            "8abc2014-5c23-42a9-9ba7-0b106e9158d2": "",
            "b816ade1-bef2-42de-9d6f-4c389b8c16a5": "",
            "bc180d95-6234-45ef-a7eb-b3344c25013b": "",
            "20f8d6b0-0f96-4f1a-9547-24c947b7b5c6": "0.00"
          }
        ]
      },
      "position": {
        "x": 960,
        "y": 300
      }
    },
    {
      "id": "ebafd303-636a-4a73-a360-698dabacebaa",
      "name": "Couple & Dependents",
      "type": "decisionTableNode",
      "content": {
        "hitPolicy": "first",
        "inputs": [
          {
            "id": "f60aecf1-41b4-46cb-be41-da2a321eace7",
            "name": "Person 1 Age",
            "type": "expression",
            "field": "person1age"
          },
          {
            "id": "2228d8e9-e32a-47f2-8905-dcd24315fb44",
            "name": "Person 1 PPMB Status",
            "type": "expression",
            "field": "person1hasPPMBStatus"
          },
          {
            "id": "4487d5a3-b08e-4925-9278-cc8fa223f4c3",
            "type": "expression",
            "field": "person1Warrant",
            "name": "Person 1 Warrant Issued"
          },
          {
            "id": "8abc2014-5c23-42a9-9ba7-0b106e9158d2",
            "name": "Person 2 Age",
            "type": "expression",
            "field": "person2age"
          },
          {
            "id": "b816ade1-bef2-42de-9d6f-4c389b8c16a5",
            "name": "Person 2 PPMB Status",
            "type": "expression",
            "field": "person2hasPPMBStatus"
          },
          {
            "id": "bc180d95-6234-45ef-a7eb-b3344c25013b",
            "type": "expression",
            "field": "person2Warrant",
            "name": "Person 2 Warrant Issued"
          }
        ],
        "outputs": [
          {
            "id": "20f8d6b0-0f96-4f1a-9547-24c947b7b5c6",
            "name": "Maximum Support Amount",
            "type": "expression",
            "field": "maximumSupportAmount"
          }
        ],
        "rules": [
          {
            "_id": "1f0000ea-9710-4dd9-a8aa-129bd8091ebb",
            "_description": "Both applicants/recipients are under 65 years of age, and a warrant has been issued for one",
            "f60aecf1-41b4-46cb-be41-da2a321eace7": "< 65",
            "2228d8e9-e32a-47f2-8905-dcd24315fb44": "false",
            "4487d5a3-b08e-4925-9278-cc8fa223f4c3": "true",
            "8abc2014-5c23-42a9-9ba7-0b106e9158d2": "< 65",
            "b816ade1-bef2-42de-9d6f-4c389b8c16a5": "false",
            "bc180d95-6234-45ef-a7eb-b3344c25013b": "== null or == false",
            "20f8d6b0-0f96-4f1a-9547-24c947b7b5c6": "955"
          },
          {
            "_id": "e592c9e8-8f70-4b62-b987-5dc6dcb952da",
            "_description": "Both applicants/recipients are under 65 years of age, and a warrant has been issued for one",
            "f60aecf1-41b4-46cb-be41-da2a321eace7": "< 65",
            "2228d8e9-e32a-47f2-8905-dcd24315fb44": "false",
            "4487d5a3-b08e-4925-9278-cc8fa223f4c3": "== null or == false",
            "8abc2014-5c23-42a9-9ba7-0b106e9158d2": "< 65",
            "b816ade1-bef2-42de-9d6f-4c389b8c16a5": "false",
            "bc180d95-6234-45ef-a7eb-b3344c25013b": "true",
            "20f8d6b0-0f96-4f1a-9547-24c947b7b5c6": "955"
          },
          {
            "_id": "2712edc4-6186-468f-806c-56ea2fa92b36",
            "_description": "Both applicants/recipients are under 65 years of age, and a warrant has been issued for both",
            "f60aecf1-41b4-46cb-be41-da2a321eace7": "< 65",
            "2228d8e9-e32a-47f2-8905-dcd24315fb44": "false",
            "4487d5a3-b08e-4925-9278-cc8fa223f4c3": "true",
            "8abc2014-5c23-42a9-9ba7-0b106e9158d2": "< 65",
            "b816ade1-bef2-42de-9d6f-4c389b8c16a5": "false",
            "bc180d95-6234-45ef-a7eb-b3344c25013b": "true",
            "20f8d6b0-0f96-4f1a-9547-24c947b7b5c6": "905"
          },
          {
            "_id": "095a879b-4eee-4957-bd00-bf4edea34c4a",
            "_description": "One applicant/recipient is under 65 years of age and is a person who has persistent multiple barriers to employment, and the other is under 65 years of age, and a warrant has been issued for one",
            "f60aecf1-41b4-46cb-be41-da2a321eace7": "< 65",
            "2228d8e9-e32a-47f2-8905-dcd24315fb44": "true",
            "4487d5a3-b08e-4925-9278-cc8fa223f4c3": "true",
            "8abc2014-5c23-42a9-9ba7-0b106e9158d2": "< 65",
            "b816ade1-bef2-42de-9d6f-4c389b8c16a5": "false",
            "bc180d95-6234-45ef-a7eb-b3344c25013b": "== null or == false",
            "20f8d6b0-0f96-4f1a-9547-24c947b7b5c6": "1005"
          },
          {
            "_id": "7de0977d-43b4-455c-831c-125e0ed98329",
            "_description": "One applicant/recipient is under 65 years of age and is a person who has persistent multiple barriers to employment, and the other is under 65 years of age, and a warrant has been issued for one",
            "f60aecf1-41b4-46cb-be41-da2a321eace7": "< 65",
            "2228d8e9-e32a-47f2-8905-dcd24315fb44": "true",
            "4487d5a3-b08e-4925-9278-cc8fa223f4c3": "== null or == false",
            "8abc2014-5c23-42a9-9ba7-0b106e9158d2": "< 65",
            "b816ade1-bef2-42de-9d6f-4c389b8c16a5": "false",
            "bc180d95-6234-45ef-a7eb-b3344c25013b": "true",
            "20f8d6b0-0f96-4f1a-9547-24c947b7b5c6": "1005"
          },
          {
            "_id": "5e5bd0b0-d830-4f0f-9aee-33d3d08db4e1",
            "_description": "One applicant/recipient is under 65 years of age and is a person who has persistent multiple barriers to employment, and the other is under 65 years of age, and a warrant has been issued for one",
            "f60aecf1-41b4-46cb-be41-da2a321eace7": "< 65",
            "2228d8e9-e32a-47f2-8905-dcd24315fb44": "false",
            "4487d5a3-b08e-4925-9278-cc8fa223f4c3": "true",
            "8abc2014-5c23-42a9-9ba7-0b106e9158d2": "< 65",
            "b816ade1-bef2-42de-9d6f-4c389b8c16a5": "true",
            "bc180d95-6234-45ef-a7eb-b3344c25013b": "== null or == false",
            "20f8d6b0-0f96-4f1a-9547-24c947b7b5c6": "1005"
          },
          {
            "_id": "07f92e86-ce67-42aa-96b6-17008e314dd9",
            "_description": "One applicant/recipient is under 65 years of age and is a person who has persistent multiple barriers to employment, and the other is under 65 years of age, and a warrant has been issued for one",
            "f60aecf1-41b4-46cb-be41-da2a321eace7": "< 65",
            "2228d8e9-e32a-47f2-8905-dcd24315fb44": "false",
            "4487d5a3-b08e-4925-9278-cc8fa223f4c3": "== null or == false",
            "8abc2014-5c23-42a9-9ba7-0b106e9158d2": "< 65",
            "b816ade1-bef2-42de-9d6f-4c389b8c16a5": "true",
            "bc180d95-6234-45ef-a7eb-b3344c25013b": "true",
            "20f8d6b0-0f96-4f1a-9547-24c947b7b5c6": "1005"
          },
          {
            "_id": "6f093644-523c-44da-a8d9-86c635d06f8a",
            "_description": "One applicant/recipient is under 65 years of age and is a person who has persistent multiple barriers to employment, and the other is under 65 years of age, and a warrant has been issued for both",
            "f60aecf1-41b4-46cb-be41-da2a321eace7": "< 65",
            "2228d8e9-e32a-47f2-8905-dcd24315fb44": "false",
            "4487d5a3-b08e-4925-9278-cc8fa223f4c3": "true",
            "8abc2014-5c23-42a9-9ba7-0b106e9158d2": "< 65",
            "b816ade1-bef2-42de-9d6f-4c389b8c16a5": "true",
            "bc180d95-6234-45ef-a7eb-b3344c25013b": "true",
            "20f8d6b0-0f96-4f1a-9547-24c947b7b5c6": "955"
          },
          {
            "_id": "06a7cc69-3468-49f4-a30c-eba466cfc6db",
            "_description": "One applicant/recipient is under 65 years of age and is a person who has persistent multiple barriers to employment, and the other is under 65 years of age, and a warrant has been issued for both",
            "f60aecf1-41b4-46cb-be41-da2a321eace7": "< 65",
            "2228d8e9-e32a-47f2-8905-dcd24315fb44": "true",
            "4487d5a3-b08e-4925-9278-cc8fa223f4c3": "true",
            "8abc2014-5c23-42a9-9ba7-0b106e9158d2": "< 65",
            "b816ade1-bef2-42de-9d6f-4c389b8c16a5": "false",
            "bc180d95-6234-45ef-a7eb-b3344c25013b": "true",
            "20f8d6b0-0f96-4f1a-9547-24c947b7b5c6": "955"
          },
          {
            "_id": "ac31bab6-591f-4639-9643-2ca7ec4f6499",
            "_description": "One applicant/recipient is under 65 years of age and is a person who has persistent multiple barriers to employment, and the other is 65 years of age or older, and a warrant has been issued for one",
            "f60aecf1-41b4-46cb-be41-da2a321eace7": "< 65",
            "2228d8e9-e32a-47f2-8905-dcd24315fb44": "true",
            "4487d5a3-b08e-4925-9278-cc8fa223f4c3": "true",
            "8abc2014-5c23-42a9-9ba7-0b106e9158d2": ">= 65",
            "b816ade1-bef2-42de-9d6f-4c389b8c16a5": "",
            "bc180d95-6234-45ef-a7eb-b3344c25013b": "== null or == false",
            "20f8d6b0-0f96-4f1a-9547-24c947b7b5c6": "1255"
          },
          {
            "_id": "9ac364f8-38fe-40f1-a5ae-0abac33d968f",
            "_description": "One applicant/recipient is under 65 years of age and is a person who has persistent multiple barriers to employment, and the other is 65 years of age or older, and a warrant has been issued for one",
            "f60aecf1-41b4-46cb-be41-da2a321eace7": "< 65",
            "2228d8e9-e32a-47f2-8905-dcd24315fb44": "true",
            "4487d5a3-b08e-4925-9278-cc8fa223f4c3": "== null or == false",
            "8abc2014-5c23-42a9-9ba7-0b106e9158d2": ">= 65",
            "b816ade1-bef2-42de-9d6f-4c389b8c16a5": "",
            "bc180d95-6234-45ef-a7eb-b3344c25013b": "true",
            "20f8d6b0-0f96-4f1a-9547-24c947b7b5c6": "1255"
          },
          {
            "_id": "ca24b4c8-091c-4499-8e24-ea19f2ac5a0e",
            "_description": "One applicant/recipient is under 65 years of age and is a person who has persistent multiple barriers to employment, and the other is 65 years of age or older, and a warrant has been issued for one",
            "f60aecf1-41b4-46cb-be41-da2a321eace7": ">= 65",
            "2228d8e9-e32a-47f2-8905-dcd24315fb44": "",
            "4487d5a3-b08e-4925-9278-cc8fa223f4c3": "true",
            "8abc2014-5c23-42a9-9ba7-0b106e9158d2": "< 65",
            "b816ade1-bef2-42de-9d6f-4c389b8c16a5": "true",
            "bc180d95-6234-45ef-a7eb-b3344c25013b": "== null or == false",
            "20f8d6b0-0f96-4f1a-9547-24c947b7b5c6": "1255"
          },
          {
            "_id": "56f1a164-a279-4590-bc65-4c61686f75ee",
            "_description": "One applicant/recipient is under 65 years of age and is a person who has persistent multiple barriers to employment, and the other is 65 years of age or older, and a warrant has been issued for one",
            "f60aecf1-41b4-46cb-be41-da2a321eace7": ">= 65",
            "2228d8e9-e32a-47f2-8905-dcd24315fb44": "",
            "4487d5a3-b08e-4925-9278-cc8fa223f4c3": "== null or == false",
            "8abc2014-5c23-42a9-9ba7-0b106e9158d2": "< 65",
            "b816ade1-bef2-42de-9d6f-4c389b8c16a5": "true",
            "bc180d95-6234-45ef-a7eb-b3344c25013b": "true",
            "20f8d6b0-0f96-4f1a-9547-24c947b7b5c6": "1255"
          },
          {
            "_id": "3a307cb8-6e34-438a-b3b0-3fa998feabff",
            "_description": "One applicant/recipient is under 65 years of age and is a person who has persistent multiple barriers to employment, and the other is 65 years of age or older, and a warrant has been issued for both",
            "f60aecf1-41b4-46cb-be41-da2a321eace7": ">= 65",
            "2228d8e9-e32a-47f2-8905-dcd24315fb44": "",
            "4487d5a3-b08e-4925-9278-cc8fa223f4c3": "true",
            "8abc2014-5c23-42a9-9ba7-0b106e9158d2": "< 65",
            "b816ade1-bef2-42de-9d6f-4c389b8c16a5": "true",
            "bc180d95-6234-45ef-a7eb-b3344c25013b": "true",
            "20f8d6b0-0f96-4f1a-9547-24c947b7b5c6": "1205"
          },
          {
            "_id": "d071365d-11fa-46a1-8cfc-137b1f9b42c5",
            "_description": "One applicant/recipient is under 65 years of age and is a person who has persistent multiple barriers to employment, and the other is 65 years of age or older, and a warrant has been issued for both",
            "f60aecf1-41b4-46cb-be41-da2a321eace7": "< 65",
            "2228d8e9-e32a-47f2-8905-dcd24315fb44": "true",
            "4487d5a3-b08e-4925-9278-cc8fa223f4c3": "true",
            "8abc2014-5c23-42a9-9ba7-0b106e9158d2": ">= 65",
            "b816ade1-bef2-42de-9d6f-4c389b8c16a5": "",
            "bc180d95-6234-45ef-a7eb-b3344c25013b": "true",
            "20f8d6b0-0f96-4f1a-9547-24c947b7b5c6": "1205"
          },
          {
            "_id": "54f5f328-17c8-4809-86af-d3ea9b928cf8",
            "_description": "One applicant/recipient is under 65 years of age and the other is 65 years of age or older, and a warrant has been issued for one",
            "f60aecf1-41b4-46cb-be41-da2a321eace7": "< 65",
            "2228d8e9-e32a-47f2-8905-dcd24315fb44": "false",
            "4487d5a3-b08e-4925-9278-cc8fa223f4c3": "true",
            "8abc2014-5c23-42a9-9ba7-0b106e9158d2": ">= 65",
            "b816ade1-bef2-42de-9d6f-4c389b8c16a5": "",
            "bc180d95-6234-45ef-a7eb-b3344c25013b": "== null or == false",
            "20f8d6b0-0f96-4f1a-9547-24c947b7b5c6": "1255"
          },
          {
            "_id": "2baedee1-83d2-4c41-be8e-3c97185bde55",
            "_description": "One applicant/recipient is under 65 years of age and the other is 65 years of age or older, and a warrant has been issued for one",
            "f60aecf1-41b4-46cb-be41-da2a321eace7": ">= 65",
            "2228d8e9-e32a-47f2-8905-dcd24315fb44": "",
            "4487d5a3-b08e-4925-9278-cc8fa223f4c3": "true",
            "8abc2014-5c23-42a9-9ba7-0b106e9158d2": "< 65",
            "b816ade1-bef2-42de-9d6f-4c389b8c16a5": "",
            "bc180d95-6234-45ef-a7eb-b3344c25013b": "== null or == false",
            "20f8d6b0-0f96-4f1a-9547-24c947b7b5c6": "1255"
          },
          {
            "_id": "c77c25f7-f0e4-4ac9-81fc-a0b5284c2344",
            "_description": "One applicant/recipient is under 65 years of age and the other is 65 years of age or older, and a warrant has been issued for one",
            "f60aecf1-41b4-46cb-be41-da2a321eace7": "< 65",
            "2228d8e9-e32a-47f2-8905-dcd24315fb44": "false",
            "4487d5a3-b08e-4925-9278-cc8fa223f4c3": "== null or == false",
            "8abc2014-5c23-42a9-9ba7-0b106e9158d2": ">= 65",
            "b816ade1-bef2-42de-9d6f-4c389b8c16a5": "",
            "bc180d95-6234-45ef-a7eb-b3344c25013b": "true",
            "20f8d6b0-0f96-4f1a-9547-24c947b7b5c6": "1255"
          },
          {
            "_id": "1a89a19c-16b8-4c08-9679-c522547f3e40",
            "_description": "One applicant/recipient is under 65 years of age and the other is 65 years of age or older, and a warrant has been issued for one",
            "f60aecf1-41b4-46cb-be41-da2a321eace7": ">= 65",
            "2228d8e9-e32a-47f2-8905-dcd24315fb44": "",
            "4487d5a3-b08e-4925-9278-cc8fa223f4c3": "== null or == false",
            "8abc2014-5c23-42a9-9ba7-0b106e9158d2": "< 65",
            "b816ade1-bef2-42de-9d6f-4c389b8c16a5": "false",
            "bc180d95-6234-45ef-a7eb-b3344c25013b": "true",
            "20f8d6b0-0f96-4f1a-9547-24c947b7b5c6": "1255"
          },
          {
            "_id": "83d17697-0674-48fc-82ac-a928932fcc48",
            "_description": "One applicant/recipient is under 65 years of age and the other is 65 years of age or older, and a warrant has been issued for both",
            "f60aecf1-41b4-46cb-be41-da2a321eace7": "< 65",
            "2228d8e9-e32a-47f2-8905-dcd24315fb44": "false",
            "4487d5a3-b08e-4925-9278-cc8fa223f4c3": "true",
            "8abc2014-5c23-42a9-9ba7-0b106e9158d2": ">= 65",
            "b816ade1-bef2-42de-9d6f-4c389b8c16a5": "",
            "bc180d95-6234-45ef-a7eb-b3344c25013b": "true",
            "20f8d6b0-0f96-4f1a-9547-24c947b7b5c6": "1205"
          },
          {
            "_id": "6d7be4a3-50d6-4c9a-b6f1-3187cc80b221",
            "_description": "One applicant/recipient is under 65 years of age and the other is 65 years of age or older, and a warrant has been issued for both",
            "f60aecf1-41b4-46cb-be41-da2a321eace7": ">= 65",
            "2228d8e9-e32a-47f2-8905-dcd24315fb44": "",
            "4487d5a3-b08e-4925-9278-cc8fa223f4c3": "true",
            "8abc2014-5c23-42a9-9ba7-0b106e9158d2": "< 65",
            "b816ade1-bef2-42de-9d6f-4c389b8c16a5": "false",
            "bc180d95-6234-45ef-a7eb-b3344c25013b": "true",
            "20f8d6b0-0f96-4f1a-9547-24c947b7b5c6": "1205"
          },
          {
            "_id": "9df7b0de-a1b8-4792-8ab0-6d965de8c202",
            "_description": "Both applicants/recipients are 65 years of age or older, and a warrant has been issued for one",
            "f60aecf1-41b4-46cb-be41-da2a321eace7": ">= 65",
            "2228d8e9-e32a-47f2-8905-dcd24315fb44": "",
            "4487d5a3-b08e-4925-9278-cc8fa223f4c3": "== null or == false",
            "8abc2014-5c23-42a9-9ba7-0b106e9158d2": ">= 65",
            "b816ade1-bef2-42de-9d6f-4c389b8c16a5": "",
            "bc180d95-6234-45ef-a7eb-b3344c25013b": "true",
            "20f8d6b0-0f96-4f1a-9547-24c947b7b5c6": "1505"
          },
          {
            "_id": "a19e5cfe-b177-4cde-9614-18c30c578b64",
            "_description": "Both applicants/recipients are 65 years of age or older, and a warrant has been issued for one",
            "f60aecf1-41b4-46cb-be41-da2a321eace7": ">= 65",
            "2228d8e9-e32a-47f2-8905-dcd24315fb44": "",
            "4487d5a3-b08e-4925-9278-cc8fa223f4c3": "true",
            "8abc2014-5c23-42a9-9ba7-0b106e9158d2": ">= 65",
            "b816ade1-bef2-42de-9d6f-4c389b8c16a5": "",
            "bc180d95-6234-45ef-a7eb-b3344c25013b": "== null or == false",
            "20f8d6b0-0f96-4f1a-9547-24c947b7b5c6": "1505"
          },
          {
            "_id": "fe921a96-236b-46d2-9b01-56c38328cb7c",
            "_description": "Both applicants/recipients are 65 years of age or older and a warrant has been issued for both",
            "f60aecf1-41b4-46cb-be41-da2a321eace7": ">= 65",
            "2228d8e9-e32a-47f2-8905-dcd24315fb44": "",
            "4487d5a3-b08e-4925-9278-cc8fa223f4c3": "true",
            "8abc2014-5c23-42a9-9ba7-0b106e9158d2": ">= 65",
            "b816ade1-bef2-42de-9d6f-4c389b8c16a5": "",
            "bc180d95-6234-45ef-a7eb-b3344c25013b": "true",
            "20f8d6b0-0f96-4f1a-9547-24c947b7b5c6": "1455"
          },
          {
            "_id": "fec76ef4-5704-4a61-bc4a-5992a9c51948",
            "_description": "Both applicants/recipients are under 65 years of age and both have persistent multiple barriers to employment, and a warrant has been issued for one",
            "f60aecf1-41b4-46cb-be41-da2a321eace7": "< 65",
            "2228d8e9-e32a-47f2-8905-dcd24315fb44": "true",
            "4487d5a3-b08e-4925-9278-cc8fa223f4c3": "true",
            "8abc2014-5c23-42a9-9ba7-0b106e9158d2": "< 65",
            "b816ade1-bef2-42de-9d6f-4c389b8c16a5": "true",
            "bc180d95-6234-45ef-a7eb-b3344c25013b": "== null or == false",
            "20f8d6b0-0f96-4f1a-9547-24c947b7b5c6": "1055"
          },
          {
            "_id": "a99eb609-b8d6-4637-8638-70dc62ae94f6",
            "_description": "Both applicants/recipients are under 65 years of age and both have persistent multiple barriers to employment, and a warrant has been issued for one",
            "f60aecf1-41b4-46cb-be41-da2a321eace7": "< 65",
            "2228d8e9-e32a-47f2-8905-dcd24315fb44": "true",
            "4487d5a3-b08e-4925-9278-cc8fa223f4c3": "== null or == false",
            "8abc2014-5c23-42a9-9ba7-0b106e9158d2": "< 65",
            "b816ade1-bef2-42de-9d6f-4c389b8c16a5": "true",
            "bc180d95-6234-45ef-a7eb-b3344c25013b": "true",
            "20f8d6b0-0f96-4f1a-9547-24c947b7b5c6": "1055"
          },
          {
            "_id": "5694c416-8daa-4ff8-83b6-82a748fac66f",
            "_description": "Both applicants/recipients are under 65 years of age and both have persistent multiple barriers to employment, and a warrant has been issued for both",
            "f60aecf1-41b4-46cb-be41-da2a321eace7": "< 65",
            "2228d8e9-e32a-47f2-8905-dcd24315fb44": "true",
            "4487d5a3-b08e-4925-9278-cc8fa223f4c3": "true",
            "8abc2014-5c23-42a9-9ba7-0b106e9158d2": "< 65",
            "b816ade1-bef2-42de-9d6f-4c389b8c16a5": "true",
            "bc180d95-6234-45ef-a7eb-b3344c25013b": "true",
            "20f8d6b0-0f96-4f1a-9547-24c947b7b5c6": "1005"
          },
          {
            "_id": "2c6e9219-b408-4384-983f-03f74b1c0441",
            "f60aecf1-41b4-46cb-be41-da2a321eace7": "",
            "2228d8e9-e32a-47f2-8905-dcd24315fb44": "",
            "4487d5a3-b08e-4925-9278-cc8fa223f4c3": "",
            "8abc2014-5c23-42a9-9ba7-0b106e9158d2": "",
            "b816ade1-bef2-42de-9d6f-4c389b8c16a5": "",
            "bc180d95-6234-45ef-a7eb-b3344c25013b": "",
            "20f8d6b0-0f96-4f1a-9547-24c947b7b5c6": "0.00"
          }
        ]
      },
      "position": {
        "x": 975,
        "y": 110
      }
    }
  ],
  "edges": [
    {
      "id": "fbe47bad-75f3-423e-ab99-001b93de9837",
      "type": "edge",
      "sourceId": "95a8fd76-0915-48d9-b716-11577923dd7b",
      "targetId": "42de2c3f-f9c0-4acf-93bd-f06a3adf5ef2",
      "sourceHandle": "68eabe9f-10dd-4eb3-a071-16dac264bc30"
    },
    {
      "id": "c64cf46d-8ab1-4faf-a12c-50291ace86ea",
      "type": "edge",
      "sourceId": "42de2c3f-f9c0-4acf-93bd-f06a3adf5ef2",
      "targetId": "87a78f50-78f3-4ed8-9368-bcbeb110516d"
    },
    {
      "id": "26aafec1-d88f-4144-8f2c-14711851f18b",
      "type": "edge",
      "sourceId": "0ef9b348-b509-4ccd-abf5-d3eb5f97b0d6",
      "targetId": "95a8fd76-0915-48d9-b716-11577923dd7b"
    },
    {
      "id": "b10506b7-5ed4-4b38-af66-4864b18f00aa",
      "type": "edge",
      "sourceId": "95a8fd76-0915-48d9-b716-11577923dd7b",
      "targetId": "42de2c3f-f9c0-4acf-93bd-f06a3adf5ef2",
      "sourceHandle": "71d825d5-b9e2-45a6-b106-4cbe576f379a"
    },
    {
      "id": "e6ac9914-dc8c-44db-937e-7e294689e65e",
      "sourceId": "95a8fd76-0915-48d9-b716-11577923dd7b",
      "type": "edge",
      "targetId": "b96f4ee8-7085-484c-b4cd-16990d429dbf",
      "sourceHandle": "371816d5-dfad-494e-af27-f68367b8a574"
    },
    {
      "id": "185795c0-711b-4b04-91c0-2143bbaea396",
      "sourceId": "b96f4ee8-7085-484c-b4cd-16990d429dbf",
      "type": "edge",
      "targetId": "04bd3143-711e-4896-9598-8783989c1be2",
      "sourceHandle": "04132164-4a91-4fc3-bb56-e8e8e5d6efcd"
    },
    {
      "id": "e69e1c62-dd84-4e88-a456-c6b50cd04be1",
      "sourceId": "04bd3143-711e-4896-9598-8783989c1be2",
      "type": "edge",
      "targetId": "87a78f50-78f3-4ed8-9368-bcbeb110516d"
    },
    {
      "id": "f7593c82-d45b-4e26-94f1-e66b750d3503",
      "sourceId": "b96f4ee8-7085-484c-b4cd-16990d429dbf",
      "type": "edge",
      "targetId": "ebafd303-636a-4a73-a360-698dabacebaa",
      "sourceHandle": "192d22af-87a0-4e28-afa1-7b24a473d106"
    },
    {
      "id": "0eaaf188-fe27-44d5-8fe5-47b277f39d38",
      "sourceId": "ebafd303-636a-4a73-a360-698dabacebaa",
      "type": "edge",
      "targetId": "87a78f50-78f3-4ed8-9368-bcbeb110516d"
    }
  ]
}